{
  "project_info": {
    "project_number": "1092730300865",
    "project_id": "mad255-firebasemessaging",
    "storage_bucket": "mad255-firebasemessaging.appspot.com"
  },
  "client": [
    {
      "client_info": {
        "mobilesdk_app_id": "1:1092730300865:android:a0f7786278f803675fa740",
        "android_client_info": {
          "package_name": "com.example.mad255_firebasemessaging"
        }
      },
      "oauth_client": [
        {
          "client_id": "1092730300865-gfaqi4tguaog44dmka6qtlh1g0quboei.apps.googleusercontent.com",
          "client_type": 3
        }
      ],
      "api_key": [
        {
          "current_key": "AIzaSyCbzGZu7fcmw3LnoHw_bSKsJVkUIJZaVWk"
        }
      ],
      "services": {
        "appinvite_service": {
          "other_platform_oauth_client": [
            {
              "client_id": "1092730300865-gfaqi4tguaog44dmka6qtlh1g0quboei.apps.googleusercontent.com",
              "client_type": 3
            }
          ]
        }
      }
    }
  ],
  "configuration_version": "1"
}